{"OSCILLATORS": [{"algorithm": 6}, {"attack_factor": 1.0, "freq_decimal": 0, "decay_additive": 1.0, "decay_factor": 1.0, "sustain_additive": 1.0, "frequency": 5, "sustain_factor": 1.0, "waveshape": 6, "amplitude": 0, "feedback": 0, "attack_additive": 1.0, "oscillator": 0}, {"attack_factor": 1.0, "freq_decimal": 0, "decay_additive": 1.0, "decay_factor": 1.0, "sustain_additive": 1.0, "frequency": 6, "sustain_factor": 1.0, "waveshape": 0, "amplitude": 0, "feedback": 0, "attack_additive": 1.0, "oscillator": 1}, {"attack_factor": 1.0, "freq_decimal": 0, "decay_additive": 1.0, "decay_factor": 1.0, "sustain_additive": 1.0, "frequency": 3, "sustain_factor": 1.0, "waveshape": 2, "amplitude": 0, "feedback": 3, "attack_additive": 1.0, "oscillator": 2}, {"attack_factor": 1.0, "freq_decimal": 0, "decay_additive": 1.0, "decay_factor": 1.0, "sustain_additive": 1.0, "frequency": 2, "sustain_factor": 1.0, "waveshape": 2, "amplitude": 0, "feedback": 0, "attack_additive": 1.0, "oscillator": 3}], "VCA": {"CURSOR": 3, "ATTACK": 0.05, "DECAY": 0.649999, "ATTACK_LEVEL": 1.5, "SUSTAIN": 0.799999, "RELEASE": 0.149999, "KEYSENSE": 0}, "SAMPLING": {"CURSOR": 7, "WAVE4": "", "SAVE": 0, "SAMPLE": 0, "WAVE1": "", "WAVE2": "", "WAVE3": "", "CUT": 500, "NAME": "        ", "TIME": 1, "WAIT": 3.0}, "LOAD": {"SOUND_NAME": "", "LOAD_SOUND": 0, "BANK": 0, "CURSOR": 2, "SOUND": 73}, "SAVE": {"SOUND_NAME": "Piccolo     ", "SAVE_SOUND": 0, "BANK": 0, "CURSOR": 6, "SOUND": 73}, "FILTER": {"START_LEVEL": 0.299999, "FREQUENCY": 1100, "LFO_RATE": 0.5, "FILTER_KEYSENSE": 0, "SUSTAIN_LEVEL": 0.699998, "DECAY_TIME": 0.6, "ADSR_VELOCITY": 1.5, "MODULATION": 0, "END_LEVEL": 0.0, "ADSR_FQMAX": 100, "ADSR_QfMAX": 0.4, "CURSOR": 0, "SUSTAIN_RELEASE": 2, "TYPE": 0, "RESONANCE": 0.499992, "ATTACK_TIME": 0.2, "LFO_FQMAX": 80, "ADSR_FQ_REVS": 0, "ADSR_Qf_REVS": 0, "TIME_SPAN": 2.8}, "SOUND": {"UNISON": 0, "LFO_RATE_A": 23.0, "BANK": 0, "AMPLITUDE": 0, "SOUND": 73, "CURSOR": 4, "VOLUME": 7, "ADJUST_LEVEL": 1, "SOUND_NAME": "Piccolo     ", "VIBR": 1, "LFO_SCALE_A": 0.7, "LFO_RATE_B": 6.0, "LFO_SCALE_B": 0.0149999}, "ADDITIVEWAVE": [{"amplitude": 100, "frequency": 1, "freq_decimal": 0, "oscillator": 0}, {"amplitude": 15, "frequency": 2, "freq_decimal": 0, "oscillator": 1}, {"amplitude": 20, "frequency": 3, "freq_decimal": 0, "oscillator": 2}, {"amplitude": 13, "frequency": 4, "freq_decimal": 0, "oscillator": 3}, {"amplitude": 10, "frequency": 5, "freq_decimal": 0, "oscillator": 4}, {"amplitude": 0, "frequency": 6, "freq_decimal": 0, "oscillator": 5}, {"amplitude": 0, "frequency": 7, "freq_decimal": 0, "oscillator": 6}, {"amplitude": 0, "frequency": 8, "freq_decimal": 0, "oscillator": 7}]}